{
    "name": "tr",
    "version": "1.22",
    "revision": 2,
    "description": "Translate, squeeze, or delete chars",
    "category": "util/cli",
    "source": "OpenBSD tr.c 1.22",
    "license": "BSD",
    "size": 45901,
    "sha256": "f3726f1bb609d2d05c544f8cd9f31eb4e573c849c9d6053c979a89ea960783fc",
    "download": "/packages/tr-1.22-2.lha",
    "requires": [],
    "aminet": "",
    "stack": 16384,
    "status": "stable",
    "published_at": "2026-03-27T00:03:21Z",
    "readme": "Short:        Translate, squeeze, or delete chars\nType:         util/cli\nArchitecture: m68k-amigaos >= 3.0\nUploader:     duncan (at) bowring (dot) us\nAuthor:       OpenBSD (ported by Duncan Bowring)\nVersion:      1.22\n\ntr - Translate, squeeze, or delete chars\n\nOriginal author: OpenBSD\nPorted by Duncan Bowring using amiport (AI-assisted porting toolkit).\nProject: https://github.com/bdgscotland/amiport\n\nCross-compiled with bebbo-gcc for AmigaOS 3.x (68000+).\nTested via vamos emulator and FS-UAE with Workbench 3.1.\n\nStandalone binary, no ixemul.library needed (-noixemul).\n\nIncludes full source code (original POSIX and ported Amiga versions)\nand PORT.md documenting every transformation applied.",
    "test_count": 27,
    "test_pass": 27,
    "porting_notes": "OpenBSD tr 1.22 ported to AmigaOS 3.x. 27/27 FS-UAE tests pass. Standard amiport transformations: argv expansion, Amiga exit codes, stack cookie 16384.",
    "known_limitations": "None known.",
    "binary_size_kb": 44
}
